contra_rotor/__init__.py
contra_rotor/console.py
contra_rotor-0.1.0.dist-info/entry_points.txt
contra_rotor-0.1.0.dist-info/LICENSE
contra_rotor-0.1.0.dist-info/WHEEL
contra_rotor-0.1.0.dist-info/METADATA
contra_rotor-0.1.0.dist-info/RECORD
