Metadata-Version: 2.1
Name: contra-rotor
Version: 0.1.0
Summary: 
Home-page: https://github.com/lucasmelin/contra-rotor.git
License: MIT
Author: Lucas Melin
Author-email: lucas.melin@gmail.com
Requires-Python: >=3.8,<4.0
Classifier: License :: OSI Approved :: MIT License
Classifier: Programming Language :: Python :: 3
Classifier: Programming Language :: Python :: 3.8
Requires-Dist: apache-airflow (>=1.10.10,<2.0.0)
Requires-Dist: click (>=7.1.2,<8.0.0)
Requires-Dist: requests (>=2.24.0,<3.0.0)
Project-URL: Repository, https://github.com/lucasmelin/contra-rotor.git
